pycalima/Calima.py
pycalima/__init__.py
pycalima/cmdline.py
CalimaPython-2.2.0.dist-info/LICENSE
CalimaPython-2.2.0.dist-info/METADATA
CalimaPython-2.2.0.dist-info/WHEEL
CalimaPython-2.2.0.dist-info/entry_points.txt
CalimaPython-2.2.0.dist-info/top_level.txt
CalimaPython-2.2.0.dist-info/RECORD
