Metadata-Version: 2.1
Name: CalimaPython
Version: 2.2.0
Summary: Python interface for Pax Calima Fan
Home-page: https://github.com/PotatisGrizen/pycalima
Author: Super
Author-email: unknown@unknown.com
License: Apache 2.0
Keywords: pax calima fan bluetooth ble
License-File: LICENSE
Requires-Dist: bleak
